lab/__init__.py
lab/checks.py
lab/cli.py
lab/experiment/__init__.py
lab/experiment/cli.py
lab/experiment/experiment.py
lab/project/__init__.py
lab/project/cli.py
lab_ml-0.82.dist-info/LICENSE.txt
lab_ml-0.82.dist-info/METADATA
lab_ml-0.82.dist-info/WHEEL
lab_ml-0.82.dist-info/entry_points.txt
lab_ml-0.82.dist-info/top_level.txt
lab_ml-0.82.dist-info/RECORD
