Metadata-Version: 2.1
Name: lab-ml
Version: 0.82
Summary: Lab: a command line interface for the management of arbitrary machine learning tasks.
Home-page: https://github.com/beringresearch/lab
Author: Ignat Drozdov
Author-email: idrozdov@beringresearch.com
License: Apache License 2.0
Keywords: ml ai
Platform: UNKNOWN
Classifier: Intended Audience :: Developers
Classifier: Programming Language :: Python :: 3.6
Classifier: Operating System :: OS Independent
Requires-Dist: click (>=6.7)
Requires-Dist: minio
Requires-Dist: numpy
Requires-Dist: pandas
Requires-Dist: pyyaml
Requires-Dist: tabulate
Requires-Dist: graphviz
Requires-Dist: joblib
